lintML/__init__.py
lintML/ipynb_convert.py
lintML/lintML.py
lintML/observation.py
lintML/report.py
lintML/schemas/__init__.py
lintML/schemas/observation.avsc
lintML/semgrep.py
lintML/semgrep_rules/draft/tarfile-extractall-traversal.yaml
lintML/semgrep_rules/draft/tensorflow-load-library.yaml
lintML/semgrep_rules/ready/huggingface-remote-code.yaml
lintML/semgrep_rules/ready/pickles.yaml
lintML/semgrep_rules/ready/sg_shelve.yaml
lintML/semgrep_rules/ready/tob_pickles-in-numpy.yaml
lintML/semgrep_rules/ready/tob_pickles-in-pandas.yaml
lintML/semgrep_rules/ready/tob_pickles-in-pytorch.yaml
lintML/semgrep_rules/ready/tob_scikit-joblib-load.yaml
lintML/trufflehog.py
lintML/utils.py
lintml-0.0.5.dist-info/LICENSE
lintml-0.0.5.dist-info/METADATA
lintml-0.0.5.dist-info/WHEEL
lintml-0.0.5.dist-info/entry_points.txt
lintml-0.0.5.dist-info/RECORD
