Metadata-Version: 2.1
Name: lintml
Version: 0.0.5
Summary: A security-first linter for machine learning training code.
License: GPL-3.0-only
Author: Joseph Lucas
Author-email: joe@joetl.com
Requires-Python: >=3.11,<4.0
Classifier: License :: OSI Approved :: GNU General Public License v3 (GPLv3)
Classifier: Programming Language :: Python :: 3
Classifier: Programming Language :: Python :: 3.11
Requires-Dist: asttokens (==2.4.0)
Requires-Dist: attrs (==23.1.0)
Requires-Dist: avro (==1.11.2)
Requires-Dist: backcall (==0.2.0)
Requires-Dist: beautifulsoup4 (==4.12.2)
Requires-Dist: bleach (==6.0.0)
Requires-Dist: certifi (==2023.7.22)
Requires-Dist: charset-normalizer (==3.2.0)
Requires-Dist: decorator (==5.1.1)
Requires-Dist: defusedxml (==0.7.1)
Requires-Dist: docker (==6.1.3)
Requires-Dist: executing (==1.2.0)
Requires-Dist: fastavro (==1.8.3)
Requires-Dist: fastjsonschema (==2.18.0)
Requires-Dist: idna (==3.4)
Requires-Dist: importlib-resources (>=6.0.1,<7.0.0)
Requires-Dist: ipython (==8.15.0)
Requires-Dist: jedi (==0.19.0)
Requires-Dist: jinja2 (==3.1.2)
Requires-Dist: jsonschema (==4.19.0)
Requires-Dist: jsonschema-specifications (==2023.7.1)
Requires-Dist: jupyter-client (==8.3.1)
Requires-Dist: jupyter-core (==5.3.1)
Requires-Dist: jupyterlab-pygments (==0.2.2)
Requires-Dist: markupsafe (==2.1.3)
Requires-Dist: matplotlib-inline (==0.1.6)
Requires-Dist: mistune (==3.0.1)
Requires-Dist: nbclient (==0.8.0)
Requires-Dist: nbconvert (==7.8.0)
Requires-Dist: nbformat (==5.9.2)
Requires-Dist: packaging (==23.1)
Requires-Dist: pandocfilters (==1.5.0)
Requires-Dist: parso (==0.8.3)
Requires-Dist: pexpect (==4.8.0)
Requires-Dist: pickleshare (==0.7.5)
Requires-Dist: pip (==23.2.1)
Requires-Dist: platformdirs (==3.10.0)
Requires-Dist: pre-commit (>=3.4.0,<4.0.0)
Requires-Dist: prompt-toolkit (==3.0.39)
Requires-Dist: ptyprocess (==0.7.0)
Requires-Dist: pure-eval (==0.2.2)
Requires-Dist: pygments (==2.16.1)
Requires-Dist: python-dateutil (==2.8.2)
Requires-Dist: pyzmq (==25.1.1)
Requires-Dist: referencing (==0.30.2)
Requires-Dist: requests (==2.31.0)
Requires-Dist: rpds-py (==0.10.2)
Requires-Dist: setuptools (==68.1.2)
Requires-Dist: six (==1.16.0)
Requires-Dist: soupsieve (==2.5)
Requires-Dist: stack-data (==0.6.2)
Requires-Dist: tinycss2 (==1.2.1)
Requires-Dist: tornado (==6.3.3)
Requires-Dist: traitlets (==5.9.0)
Requires-Dist: urllib3 (==2.0.4)
Requires-Dist: wcwidth (==0.2.6)
Requires-Dist: webencodings (==0.5.1)
Requires-Dist: websocket-client (==1.6.2)
Requires-Dist: wheel (==0.41.2)
